.gitignore
README.md
environment.yaml
setup.py
figures/Xenomake Workflow.png
figures/config.png
figures/human_mouse_split.jpg
figures/scanpy_qc.png
xenomake/__init__.py
xenomake/config.py
xenomake/errors.py
xenomake/smk.py
xenomake/utils.py
xenomake.egg-info/PKG-INFO
xenomake.egg-info/SOURCES.txt
xenomake.egg-info/dependency_links.txt
xenomake.egg-info/entry_points.txt
xenomake.egg-info/requires.txt
xenomake.egg-info/top_level.txt
xenomake/data/config_structure.yaml
xenomake/data/defaults_runmode.yaml
xenomake/data/defaults_spatmode.yaml
xenomake/data/picard.jar
xenomake/data/Drop-seq_tools-2.5.3/AssignCellsToSamples
xenomake/data/Drop-seq_tools-2.5.3/BamTagHistogram
xenomake/data/Drop-seq_tools-2.5.3/BamTagOfTagCounts
xenomake/data/Drop-seq_tools-2.5.3/BaseDistributionAtReadPosition
xenomake/data/Drop-seq_tools-2.5.3/BipartiteRabiesVirusCollapse
xenomake/data/Drop-seq_tools-2.5.3/CensusSeq
xenomake/data/Drop-seq_tools-2.5.3/CollapseBarcodesInPlace
xenomake/data/Drop-seq_tools-2.5.3/CollapseTagWithContext
xenomake/data/Drop-seq_tools-2.5.3/CompareDropSeqAlignments
xenomake/data/Drop-seq_tools-2.5.3/ComputeUMISharing
xenomake/data/Drop-seq_tools-2.5.3/ConvertTagToReadGroup
xenomake/data/Drop-seq_tools-2.5.3/ConvertToRefFlat
xenomake/data/Drop-seq_tools-2.5.3/CountUnmatchedSampleIndices
xenomake/data/Drop-seq_tools-2.5.3/CreateIntervalsFiles
xenomake/data/Drop-seq_tools-2.5.3/CreateMetaCells
xenomake/data/Drop-seq_tools-2.5.3/CreateSnpIntervalFromVcf
xenomake/data/Drop-seq_tools-2.5.3/CsiAnalysis
xenomake/data/Drop-seq_tools-2.5.3/DetectBeadSubstitutionErrors
xenomake/data/Drop-seq_tools-2.5.3/DetectBeadSynthesisErrors
xenomake/data/Drop-seq_tools-2.5.3/DetectDoublets
xenomake/data/Drop-seq_tools-2.5.3/DigitalExpression
xenomake/data/Drop-seq_tools-2.5.3/DownsampleBamByTag
xenomake/data/Drop-seq_tools-2.5.3/DownsampleTranscriptsAndQuantiles
xenomake/data/Drop-seq_tools-2.5.3/Drop-seq_Alignment_Cookbook.pdf
xenomake/data/Drop-seq_tools-2.5.3/Drop-seq_alignment.sh
xenomake/data/Drop-seq_tools-2.5.3/FilterBam
xenomake/data/Drop-seq_tools-2.5.3/FilterBamByGeneFunction
xenomake/data/Drop-seq_tools-2.5.3/FilterBamByTag
xenomake/data/Drop-seq_tools-2.5.3/FilterDge
